CMakeLists.txt
MANIFEST.in
README.rst
setup.py
account/CMakeLists.txt
account/__init__.py
account/account.cpp
account/account.hpp
account/test.py
account/version.py
account_zx.egg-info/PKG-INFO
account_zx.egg-info/SOURCES.txt
account_zx.egg-info/dependency_links.txt
account_zx.egg-info/top_level.txt